pycego-1.3.0.dist-info/RECORD
pycego-1.3.0.dist-info/WHEEL
pycego-1.3.0.dist-info/METADATA
pycego-1.3.0.dist-info/licenses/LICENSE
PyCEGO/PyCEGO.cpython-312-darwin.so
