Metadata-Version: 2.1
Name: pycego
Version: 1.3.0
Summary: C++->python wrapper of C++11 Evolutionary Global Optimization (CEGO)
Author-Email: Ian Bell <ian.bell@nist.gov>
Requires-Python: >=3.8
